Metadata-Version: 2.1
Name: EmailBomber
Version: 0.6
Summary: This package will allow you to send bulk emails
Home-page: https://github.com/JavaHunt
Author: Mallela Pardha Saradhi
Author-email: pardhu9100@example.com
License: MIT
Keywords: Email,Email Bomber,Bulk mails,Gmail,Smtp,Email sender
Platform: UNKNOWN
Classifier: Development Status :: 3 - Alpha
Classifier: Intended Audience :: Developers
Classifier: Topic :: Software Development :: Build Tools
Classifier: License :: OSI Approved :: MIT License
Classifier: Programming Language :: Python :: 3
Classifier: Programming Language :: Python :: 3.4
Classifier: Programming Language :: Python :: 3.5
Classifier: Programming Language :: Python :: 3.6
Classifier: Programming Language :: Python :: 3.7
Classifier: Programming Language :: Python :: 3.8
Classifier: Programming Language :: Python :: 3.9
Classifier: Programming Language :: Python :: 3.10
Classifier: Programming Language :: Python :: 3.11
